Metadata-Version: 2.1
Name: prettyparser
Version: 1.0.15
Summary: Library for Parsing PDF/TXT and Python Objects with Text Using Regular Expressions
Home-page: https://github.com/leandroroser/prettyparser
Author: Leandro Roser
Author-email: learoser@gmail.com
License: ASL
Platform: UNKNOWN
Requires-Python: >=3.6
License-File: LICENSE.txt
